nielsen/__init__.py
nielsen/config.py
nielsen/fetcher.py
nielsen/media.py
nielsen/processor.py
nielsen/bin/__init__.py
nielsen/bin/pickler.py
nielsen/bin/cli/__init__.py
nielsen/bin/cli/config.py
nielsen/bin/cli/main.py
nielsen/bin/cli/tv.py
nielsen/fetcher/tvmaze-types.py
nielsen-3.1.6.dist-info/METADATA
nielsen-3.1.6.dist-info/WHEEL
nielsen-3.1.6.dist-info/entry_points.txt
nielsen-3.1.6.dist-info/licenses/LICENSE
nielsen-3.1.6.dist-info/RECORD
