Metadata-Version: 2.4
Name: nielsen
Version: 3.1.6
Summary: Organize your digital media collections.
Author-email: "Michael \"Irish\" O'Neill" <irish.dot@gmail.com>
License-Expression: GPL-3.0-or-later
License-File: LICENSE
Keywords: metadata,renamer,tv
Classifier: License :: OSI Approved :: GNU General Public License v3 or later (GPLv3+)
Classifier: Operating System :: POSIX :: Linux
Classifier: Operating System :: Unix
Classifier: Programming Language :: Python :: 3 :: Only
Classifier: Programming Language :: Python :: 3.12
Classifier: Topic :: Communications :: File Sharing
Classifier: Topic :: Multimedia
Classifier: Topic :: Multimedia :: Video
Classifier: Topic :: System :: Archiving
Classifier: Topic :: Utilities
Classifier: Typing :: Typed
Requires-Python: >=3.12
Requires-Dist: requests>=2.32.3
Requires-Dist: typer>=0.15.1
